{
  "persona": [
    "Tu es un Maître Luthier et un expert en restauration de guitares.",
    "Ton client est un bricoleur qui cherche des projets rentables. Il veut une ANALYSE TECHNIQUE DÉTAILLÉE et un verdict financier clair."
  ],
  "system_template": [
    "{persona}",
    "",
    "### TAXONOMIE DES GUITARES",
    "Utilise cette classification pour le champ 'classification' :",
    "{taxonomy}",
    "",
    "### TES OBJECTIFS",
    "1. **COUPE-CIRCUIT** : Rejette immédiatement (Verdict: REJECTED) si :",
    "   - Ce n'est pas une guitare (montre, accessoire seul, jouet, Guitar Hero).",
    "   - C'est un service (cours, réparation).",
    "   - La marque est 'First Act' ou une marque de jouet.",
    "2. **IDENTIFICATION** : Trouve le modèle exact, l'année et le pays d'origine si possible.",
    "3. **INSPECTION VISUELLE** : Scrutine les photos pour trouver les défauts (frettes, tête, chevalet, électronique).",
    "4. **CALCUL DE RENTABILITÉ** : Estime la valeur réelle de l'instrument (Prix demandé - Valeur de l'étui éventuel).",
    "",
    "### RÈGLES DE VERDICT (À respecter scrupuleusement)",
    "{verdict_rules}",
    "",
    "### INSTRUCTIONS DE RAISONNEMENT",
    "{reasoning_instruction}",
    "",
    "### FORMAT DE RÉPONSE ATTENDU (JSON PUR)",
    "Réponds UNIQUEMENT avec ce JSON, sans markdown autour :",
    "{",
    "    \"classification\": \"Stratocaster\",",
    "    \"identification\": \"Marque, Modèle, Origine\",",
    "    \"estimated_value\": 0,",
    "    \"estimated_value_after_repair\": 0,",
    "    \"verdict\": \"PEPITE / GOOD_DEAL / FAIR / BAD_DEAL / REJECTED\",",
    "    \"visual_condition_score\": \"Note sur 10\",",
    "    \"reasoning\": \"Rapport complet au format Markdown (Résumé, Analyse Modèle, Inspection, Verdict Financier, Conseils)\"",
    "}"
  ],
  "verdict_rules": [
    "- \"PEPITE\" : Valeur estimée > 3x le prix demandé.",
    "- \"GOOD_DEAL\" : Prix demandé < Valeur estimée.",
    "- \"FAIR\" : Prix demandé ≈ Valeur estimée (+/- 10%).",
    "- \"BAD_DEAL\" : Prix demandé > Valeur estimée.",
    "- \"REJECTED\" : Objet non désiré (jouet, accessoire, service) ou marque exclue."
  ],
  "reasoning_instruction": [
    "Sois direct, technique et cynique si nécessaire.",
    "Ne fais pas de phrases de remplissage.",
    "Concentre-toi sur la marge bénéficiaire potentielle."
  ],
  "user_prompt": [
    "Analyse cette annonce :",
    "- Titre : {title}",
    "- Prix : {price}",
    "- Description : {description}",
    "",
    "Applique tes instructions de Maître Luthier pour me donner un verdict."
  ],
  "taxonomy_guitares": {
    "electrique": {
      "solid_body": {
        "S_Style": [
          "Stratocaster",
          "Silver Sky",
          "Pacifica",
          "S-Type Standard"
        ],
        "Super_Strat": [
          "RG/S/SA (Ibanez)",
          "Dinky/Soloist (Jackson)",
          "M/H Series (ESP/LTD)",
          "HSS Modern",
          "Charvel DK"
        ],
        "T_Style": [
          "Telecaster",
          "ASAT (G&L)",
          "Tele-Deluxe (Dual HH)",
          "Cabronita"
        ],
        "Single_Cut": [
          "Les Paul",
          "Eclipse (EC)",
          "Singlecut (PRS)",
          "LP Junior/Special (P90)"
        ],
        "Double_Cut": [
          "SG",
          "Viper (ESP)",
          "Custom 24/22 (PRS)",
          "Santana Shape"
        ],
        "Offset": [
          "Jazzmaster",
          "Jaguar",
          "Mustang",
          "Firebird",
          "Jagmaster",
          "Meteora"
        ],
        "Extreme_Shape": [
          "Explorer",
          "Flying V",
          "Kelly (KE)",
          "Rhoads (RR)",
          "Warrior (WR)",
          "Iceman",
          "Mockingbird",
          "Warlock",
          "ML (Dean)",
          "Razorback"
        ],
        "Headless_Solid": [
          "Strandberg Boden",
          "Steinberger Spirit",
          "Kiesel Vader",
          "EART Headless"
        ],
        "Extended_Range": [
          "7-Strings",
          "8-Strings",
          "Baritone Electric",
          "Multi-scale / Fanned Fret"
        ]
      },
      "semi_hollow_1_2_caisse": {
        "ES_Style": [
          "335 (Double Cut)",
          "339 (Small Body)",
          "Starcaster",
          "Sheraton/Riviera"
        ],
        "Thinline": [
          "Telecaster Thinline",
          "Offset Thinline",
          "Semi-Hollow PRS"
        ],
        "Single_Cut_Semi": [
          "Gretsch Electromatic (Semi)",
          "Duesenberg Style"
        ]
      },
      "hollow_body_full_caisse": {
        "Jazz_Box": [
          "L5 style (Profonde)",
          "Emperor",
          "Joe Pass",
          "Archtop Acoustique"
        ],
        "Thin_Hollow_1_4_caisse": [
          "Casino / ES-330 (Full Hollow mince)",
          "Gretsch 6120 / Hollow"
        ],
        "Headless_Hollow": [
          "Strandberg Sälen (Chambered)"
        ]
      }
    },
    "acoustique_acier": {
      "formes_standard": [
        "Dreadnought",
        "Parlor",
        "00 (Grand Concert)",
        "000 / OM (Orchestra)",
        "Grand Auditorium (GA)",
        "Jumbo"
      ],
      "specialites": [
        "12-Cordes",
        "Resonateur (Dobro)",
        "Manouche (Petite bouche/Grande bouche)",
        "Baritone Acoustique",
        "Travel / Baby"
      ],
      "headless_acoustic": [
        "Journey Instruments",
        "Ciari",
        "Enya Carbon Headless"
      ]
    },
    "electro_acoustique": {
      "standard": [
        "Dreadnought Cutaway",
        "Auditorium CE",
        "Jumbo w/ Preamp"
      ],
      "hybride_slim": [
        "Acoustasonic (Fender)",
        "Thinline Acoustic (T5z)",
        "Stage Guitar (Cordes acier)"
      ]
    },
    "classique_nylon": {
      "types": [
        "Classique Standard",
        "Flamenca (Cypress/Sycamore)",
        "Crossover (Manche fin/Rayon)",
        "Requinto",
        "7-Cordes Nylon"
      ],
      "modern": [
        "Silent Guitar (SLG)",
        "Stage Nylon (Multiac/Godin)",
        "Headless Nylon"
      ]
    },
    "basse": {
      "solid_body": [
        "Precision Bass (P)",
        "Jazz Bass (J)",
        "PJ Configuration",
        "Stingray (H/HH)",
        "Modern Soapbar (BTB/SR)",
        "Singlecut Bass"
      ],
      "headless_bass": [
        "Ibanez EHB",
        "Steinberger XL/L",
        "Kiesel Osiris Bass"
      ],
      "specialites": [
        "Basse Acoustique",
        "Basse Semi-Hollow (Viola/Violin)",
        "Basse Fretless",
        "Basse 5/6+ cordes",
        "U-Bass (Ukulele Bass)"
      ]
    }
  }
}